LICENSE
NOTICE
README.md
setup.py
core/AutoTemplate.html
core/DrawFree.html
core/DrawOperate.js
core/MetricFlow.js
core/StableTemplate.html
core/__init__.py
core/colorpicker.min.js
core/config.py
core/constant.py
core/dream-msg.min.js
core/parse.py
core/server.py
core/theme.py
draw/__init__.py
draw/graph.py
draw/node.py
ndraw/__init__.py
ndraw.egg-info/PKG-INFO
ndraw.egg-info/SOURCES.txt
ndraw.egg-info/dependency_links.txt
ndraw.egg-info/top_level.txt