Metadata-Version: 2.1
Name: ndraw
Version: 1.2.5
Summary: a tool to show neural networks and draw custom networks.
Home-page: https://gitee.com/huoyo/ndraw
Author: Chang Zhang
Author-email: 1729913829@qq.com
License: Apache License
Platform: UNKNOWN
License-File: LICENSE
License-File: NOTICE
